{
  "timeZone": "Europe/Tirane",
  "dependencies": {},
  "exceptionLogging": "STACKDRIVER",
  "runtimeVersion": "V8",
  "oauthScopes": [
    "https://www.googleapis.com/auth/gmail.readonly",
    "https://www.googleapis.com/auth/gmail.addons.current.message.readonly",
    "https://www.googleapis.com/auth/script.external_request",
    "https://www.googleapis.com/auth/script.locale",
    "https://www.googleapis.com/auth/drive.readonly"
  ],
  "addOns": {
    "common": {
      "name": "Kërko në Gmail",
      "logoUrl": "https://www.gstatic.com/images/icons/material/system/1x/search_goog_48dp.png",
      "useLocaleFromApp": true,
      "homepageTrigger": {
        "runFunction": "onHomepage",
        "enabled": true
      }
    },
    "gmail": {
      "contextualTriggers": [{
        "unconditional": {},
        "onTriggerFunction": "onGmailSidebar"
      }],
      "homepageTrigger": {
        "runFunction": "onHomepage",
        "enabled": true
      }
    }
  }
}
